pbjson/__init__.py
pbjson/_speedups.c
pbjson/compat.py
pbjson/decoder.py
pbjson/encoder.py
pbjson/tokens.py
pbjson/tool.py
pbjson/tests/__init__.py
pbjson/tests/test_check_circular.py
pbjson/tests/test_custom.py
pbjson/tests/test_decode.py
pbjson/tests/test_default.py
pbjson/tests/test_encode.py
pbjson/tests/test_float.py
pbjson/tests/test_for_json.py
pbjson/tests/test_item_sort_key.py
pbjson/tests/test_mapping.py
pbjson/tests/test_pass1.py
pbjson/tests/test_pass2.py
pbjson/tests/test_speedups.py
pbjson/tests/test_tuple.py
pbjson/tests/test_unicode.py
pbjson-1.16.0.dist-info/METADATA
pbjson-1.16.0.dist-info/WHEEL
pbjson-1.16.0.dist-info/licenses/LICENSE
pbjson-1.16.0.dist-info/RECORD
